{"nodes": [{"id": "ffa_app_tools_logging_view_logs_py", "label": "view_logs.py", "file_type": "code", "source_file": "ffa-app/tools/logging/view_logs.py", "source_location": "L1"}, {"id": "view_logs_read_logs", "label": "read_logs()", "file_type": "code", "source_file": "ffa-app/tools/logging/view_logs.py", "source_location": "L17"}, {"id": "view_logs_print_event", "label": "print_event()", "file_type": "code", "source_file": "ffa-app/tools/logging/view_logs.py", "source_location": "L63"}, {"id": "view_logs_get_statistics", "label": "get_statistics()", "file_type": "code", "source_file": "ffa-app/tools/logging/view_logs.py", "source_location": "L104"}, {"id": "view_logs_main", "label": "main()", "file_type": "code", "source_file": "ffa-app/tools/logging/view_logs.py", "source_location": "L174"}, {"id": "view_logs_rationale_23", "label": "Lee y filtra los logs          Args:         log_file: Ruta al archivo de log", "file_type": "rationale", "source_file": "ffa-app/tools/logging/view_logs.py", "source_location": "L23"}, {"id": "view_logs_rationale_64", "label": "Imprime un evento de forma legible", "file_type": "rationale", "source_file": "ffa-app/tools/logging/view_logs.py", "source_location": "L64"}, {"id": "view_logs_rationale_105", "label": "Muestra estad\u00edsticas de los logs", "file_type": "rationale", "source_file": "ffa-app/tools/logging/view_logs.py", "source_location": "L105"}], "edges": [{"source": "ffa_app_tools_logging_view_logs_py", "target": "json", "relation": "imports", "confidence": "EXTRACTED", "source_file": "ffa-app/tools/logging/view_logs.py", "source_location": "L6", "weight": 1.0}, {"source": "ffa_app_tools_logging_view_logs_py", "target": "sys", "relation": "imports", "confidence": "EXTRACTED", "source_file": "ffa-app/tools/logging/view_logs.py", "source_location": "L7", "weight": 1.0}, {"source": "ffa_app_tools_logging_view_logs_py", "target": "pathlib", "relation": "imports_from", "confidence": "EXTRACTED", "source_file": "ffa-app/tools/logging/view_logs.py", "source_location": "L8", "weight": 1.0}, {"source": "ffa_app_tools_logging_view_logs_py", "target": "datetime", "relation": "imports_from", "confidence": "EXTRACTED", "source_file": "ffa-app/tools/logging/view_logs.py", "source_location": "L9", "weight": 1.0}, {"source": "ffa_app_tools_logging_view_logs_py", "target": "typing", "relation": "imports_from", "confidence": "EXTRACTED", "source_file": "ffa-app/tools/logging/view_logs.py", "source_location": "L10", "weight": 1.0}, {"source": "ffa_app_tools_logging_view_logs_py", "target": "view_logs_read_logs", "relation": "contains", "confidence": "EXTRACTED", "source_file": "ffa-app/tools/logging/view_logs.py", "source_location": "L17", "weight": 1.0}, {"source": "ffa_app_tools_logging_view_logs_py", "target": "view_logs_print_event", "relation": "contains", "confidence": "EXTRACTED", "source_file": "ffa-app/tools/logging/view_logs.py", "source_location": "L63", "weight": 1.0}, {"source": "ffa_app_tools_logging_view_logs_py", "target": "view_logs_get_statistics", "relation": "contains", "confidence": "EXTRACTED", "source_file": "ffa-app/tools/logging/view_logs.py", "source_location": "L104", "weight": 1.0}, {"source": "ffa_app_tools_logging_view_logs_py", "target": "view_logs_main", "relation": "contains", "confidence": "EXTRACTED", "source_file": "ffa-app/tools/logging/view_logs.py", "source_location": "L174", "weight": 1.0}, {"source": "view_logs_read_logs", "target": "view_logs_print_event", "relation": "calls", "confidence": "EXTRACTED", "source_file": "ffa-app/tools/logging/view_logs.py", "source_location": "L53", "weight": 1.0}, {"source": "view_logs_main", "target": "view_logs_read_logs", "relation": "calls", "confidence": "EXTRACTED", "source_file": "ffa-app/tools/logging/view_logs.py", "source_location": "L178", "weight": 1.0}, {"source": "view_logs_main", "target": "view_logs_get_statistics", "relation": "calls", "confidence": "EXTRACTED", "source_file": "ffa-app/tools/logging/view_logs.py", "source_location": "L180", "weight": 1.0}, {"source": "view_logs_rationale_23", "target": "view_logs_read_logs", "relation": "rationale_for", "confidence": "EXTRACTED", "source_file": "ffa-app/tools/logging/view_logs.py", "source_location": "L23", "weight": 1.0}, {"source": "view_logs_rationale_64", "target": "view_logs_print_event", "relation": "rationale_for", "confidence": "EXTRACTED", "source_file": "ffa-app/tools/logging/view_logs.py", "source_location": "L64", "weight": 1.0}, {"source": "view_logs_rationale_105", "target": "view_logs_get_statistics", "relation": "rationale_for", "confidence": "EXTRACTED", "source_file": "ffa-app/tools/logging/view_logs.py", "source_location": "L105", "weight": 1.0}], "raw_calls": [{"caller_nid": "view_logs_read_logs", "callee": "exists", "source_file": "ffa-app/tools/logging/view_logs.py", "source_location": "L32"}, {"caller_nid": "view_logs_read_logs", "callee": "Path", "source_file": "ffa-app/tools/logging/view_logs.py", "source_location": "L32"}, {"caller_nid": "view_logs_read_logs", "callee": "print", "source_file": "ffa-app/tools/logging/view_logs.py", "source_location": "L33"}, {"caller_nid": "view_logs_read_logs", "callee": "open", "source_file": "ffa-app/tools/logging/view_logs.py", "source_location": "L37"}, {"caller_nid": "view_logs_read_logs", "callee": "strip", "source_file": "ffa-app/tools/logging/view_logs.py", "source_location": "L39"}, {"caller_nid": "view_logs_read_logs", "callee": "loads", "source_file": "ffa-app/tools/logging/view_logs.py", "source_location": "L43"}, {"caller_nid": "view_logs_read_logs", "callee": "get", "source_file": "ffa-app/tools/logging/view_logs.py", "source_location": "L46"}, {"caller_nid": "view_logs_read_logs", "callee": "get", "source_file": "ffa-app/tools/logging/view_logs.py", "source_location": "L49"}, {"caller_nid": "view_logs_read_logs", "callee": "print", "source_file": "ffa-app/tools/logging/view_logs.py", "source_location": "L60"}, {"caller_nid": "view_logs_print_event", "callee": "get", "source_file": "ffa-app/tools/logging/view_logs.py", "source_location": "L65"}, {"caller_nid": "view_logs_print_event", "callee": "get", "source_file": "ffa-app/tools/logging/view_logs.py", "source_location": "L66"}, {"caller_nid": "view_logs_print_event", "callee": "get", "source_file": "ffa-app/tools/logging/view_logs.py", "source_location": "L67"}, {"caller_nid": "view_logs_print_event", "callee": "get", "source_file": "ffa-app/tools/logging/view_logs.py", "source_location": "L70"}, {"caller_nid": "view_logs_print_event", "callee": "print", "source_file": "ffa-app/tools/logging/view_logs.py", "source_location": "L77"}, {"caller_nid": "view_logs_print_event", "callee": "get", "source_file": "ffa-app/tools/logging/view_logs.py", "source_location": "L80"}, {"caller_nid": "view_logs_print_event", "callee": "print", "source_file": "ffa-app/tools/logging/view_logs.py", "source_location": "L81"}, {"caller_nid": "view_logs_print_event", "callee": "get", "source_file": "ffa-app/tools/logging/view_logs.py", "source_location": "L83"}, {"caller_nid": "view_logs_print_event", "callee": "print", "source_file": "ffa-app/tools/logging/view_logs.py", "source_location": "L84"}, {"caller_nid": "view_logs_print_event", "callee": "get", "source_file": "ffa-app/tools/logging/view_logs.py", "source_location": "L86"}, {"caller_nid": "view_logs_print_event", "callee": "print", "source_file": "ffa-app/tools/logging/view_logs.py", "source_location": "L87"}, {"caller_nid": "view_logs_print_event", "callee": "dumps", "source_file": "ffa-app/tools/logging/view_logs.py", "source_location": "L87"}, {"caller_nid": "view_logs_print_event", "callee": "get", "source_file": "ffa-app/tools/logging/view_logs.py", "source_location": "L89"}, {"caller_nid": "view_logs_print_event", "callee": "print", "source_file": "ffa-app/tools/logging/view_logs.py", "source_location": "L90"}, {"caller_nid": "view_logs_print_event", "callee": "dumps", "source_file": "ffa-app/tools/logging/view_logs.py", "source_location": "L90"}, {"caller_nid": "view_logs_print_event", "callee": "get", "source_file": "ffa-app/tools/logging/view_logs.py", "source_location": "L92"}, {"caller_nid": "view_logs_print_event", "callee": "print", "source_file": "ffa-app/tools/logging/view_logs.py", "source_location": "L93"}, {"caller_nid": "view_logs_print_event", "callee": "get", "source_file": "ffa-app/tools/logging/view_logs.py", "source_location": "L95"}, {"caller_nid": "view_logs_print_event", "callee": "print", "source_file": "ffa-app/tools/logging/view_logs.py", "source_location": "L96"}, {"caller_nid": "view_logs_print_event", "callee": "get", "source_file": "ffa-app/tools/logging/view_logs.py", "source_location": "L98"}, {"caller_nid": "view_logs_print_event", "callee": "print", "source_file": "ffa-app/tools/logging/view_logs.py", "source_location": "L99"}, {"caller_nid": "view_logs_print_event", "callee": "dumps", "source_file": "ffa-app/tools/logging/view_logs.py", "source_location": "L99"}, {"caller_nid": "view_logs_print_event", "callee": "print", "source_file": "ffa-app/tools/logging/view_logs.py", "source_location": "L101"}, {"caller_nid": "view_logs_print_event", "callee": "get", "source_file": "ffa-app/tools/logging/view_logs.py", "source_location": "L101"}, {"caller_nid": "view_logs_get_statistics", "callee": "exists", "source_file": "ffa-app/tools/logging/view_logs.py", "source_location": "L106"}, {"caller_nid": "view_logs_get_statistics", "callee": "Path", "source_file": "ffa-app/tools/logging/view_logs.py", "source_location": "L106"}, {"caller_nid": "view_logs_get_statistics", "callee": "print", "source_file": "ffa-app/tools/logging/view_logs.py", "source_location": "L107"}, {"caller_nid": "view_logs_get_statistics", "callee": "open", "source_file": "ffa-app/tools/logging/view_logs.py", "source_location": "L117"}, {"caller_nid": "view_logs_get_statistics", "callee": "strip", "source_file": "ffa-app/tools/logging/view_logs.py", "source_location": "L119"}, {"caller_nid": "view_logs_get_statistics", "callee": "loads", "source_file": "ffa-app/tools/logging/view_logs.py", "source_location": "L123"}, {"caller_nid": "view_logs_get_statistics", "callee": "get", "source_file": "ffa-app/tools/logging/view_logs.py", "source_location": "L127"}, {"caller_nid": "view_logs_get_statistics", "callee": "get", "source_file": "ffa-app/tools/logging/view_logs.py", "source_location": "L128"}, {"caller_nid": "view_logs_get_statistics", "callee": "get", "source_file": "ffa-app/tools/logging/view_logs.py", "source_location": "L131"}, {"caller_nid": "view_logs_get_statistics", "callee": "get", "source_file": "ffa-app/tools/logging/view_logs.py", "source_location": "L132"}, {"caller_nid": "view_logs_get_statistics", "callee": "append", "source_file": "ffa-app/tools/logging/view_logs.py", "source_location": "L136"}, {"caller_nid": "view_logs_get_statistics", "callee": "get", "source_file": "ffa-app/tools/logging/view_logs.py", "source_location": "L137"}, {"caller_nid": "view_logs_get_statistics", "callee": "get", "source_file": "ffa-app/tools/logging/view_logs.py", "source_location": "L139"}, {"caller_nid": "view_logs_get_statistics", "callee": "get", "source_file": "ffa-app/tools/logging/view_logs.py", "source_location": "L140"}, {"caller_nid": "view_logs_get_statistics", "callee": "print", "source_file": "ffa-app/tools/logging/view_logs.py", "source_location": "L147"}, {"caller_nid": "view_logs_get_statistics", "callee": "print", "source_file": "ffa-app/tools/logging/view_logs.py", "source_location": "L148"}, {"caller_nid": "view_logs_get_statistics", "callee": "print", "source_file": "ffa-app/tools/logging/view_logs.py", "source_location": "L149"}, {"caller_nid": "view_logs_get_statistics", "callee": "print", "source_file": "ffa-app/tools/logging/view_logs.py", "source_location": "L150"}, {"caller_nid": "view_logs_get_statistics", "callee": "print", "source_file": "ffa-app/tools/logging/view_logs.py", "source_location": "L152"}, {"caller_nid": "view_logs_get_statistics", "callee": "sorted", "source_file": "ffa-app/tools/logging/view_logs.py", "source_location": "L153"}, {"caller_nid": "view_logs_get_statistics", "callee": "items", "source_file": "ffa-app/tools/logging/view_logs.py", "source_location": "L153"}, {"caller_nid": "view_logs_get_statistics", "callee": "get", "source_file": "ffa-app/tools/logging/view_logs.py", "source_location": "L155"}, {"caller_nid": "view_logs_get_statistics", "callee": "print", "source_file": "ffa-app/tools/logging/view_logs.py", "source_location": "L156"}, {"caller_nid": "view_logs_get_statistics", "callee": "print", "source_file": "ffa-app/tools/logging/view_logs.py", "source_location": "L158"}, {"caller_nid": "view_logs_get_statistics", "callee": "sorted", "source_file": "ffa-app/tools/logging/view_logs.py", "source_location": "L159"}, {"caller_nid": "view_logs_get_statistics", "callee": "items", "source_file": "ffa-app/tools/logging/view_logs.py", "source_location": "L159"}, {"caller_nid": "view_logs_get_statistics", "callee": "print", "source_file": "ffa-app/tools/logging/view_logs.py", "source_location": "L161"}, {"caller_nid": "view_logs_get_statistics", "callee": "print", "source_file": "ffa-app/tools/logging/view_logs.py", "source_location": "L164"}, {"caller_nid": "view_logs_get_statistics", "callee": "len", "source_file": "ffa-app/tools/logging/view_logs.py", "source_location": "L164"}, {"caller_nid": "view_logs_get_statistics", "callee": "print", "source_file": "ffa-app/tools/logging/view_logs.py", "source_location": "L166"}, {"caller_nid": "view_logs_get_statistics", "callee": "print", "source_file": "ffa-app/tools/logging/view_logs.py", "source_location": "L167"}, {"caller_nid": "view_logs_get_statistics", "callee": "print", "source_file": "ffa-app/tools/logging/view_logs.py", "source_location": "L168"}, {"caller_nid": "view_logs_get_statistics", "callee": "print", "source_file": "ffa-app/tools/logging/view_logs.py", "source_location": "L169"}, {"caller_nid": "view_logs_get_statistics", "callee": "print", "source_file": "ffa-app/tools/logging/view_logs.py", "source_location": "L171"}, {"caller_nid": "view_logs_main", "callee": "len", "source_file": "ffa-app/tools/logging/view_logs.py", "source_location": "L176"}, {"caller_nid": "view_logs_main", "callee": "print", "source_file": "ffa-app/tools/logging/view_logs.py", "source_location": "L177"}, {"caller_nid": "view_logs_main", "callee": "print", "source_file": "ffa-app/tools/logging/view_logs.py", "source_location": "L179"}, {"caller_nid": "view_logs_main", "callee": "print", "source_file": "ffa-app/tools/logging/view_logs.py", "source_location": "L184"}, {"caller_nid": "view_logs_main", "callee": "print", "source_file": "ffa-app/tools/logging/view_logs.py", "source_location": "L187"}, {"caller_nid": "view_logs_main", "callee": "print", "source_file": "ffa-app/tools/logging/view_logs.py", "source_location": "L190"}, {"caller_nid": "view_logs_main", "callee": "print", "source_file": "ffa-app/tools/logging/view_logs.py", "source_location": "L193"}, {"caller_nid": "view_logs_main", "callee": "print", "source_file": "ffa-app/tools/logging/view_logs.py", "source_location": "L196"}, {"caller_nid": "view_logs_main", "callee": "print", "source_file": "ffa-app/tools/logging/view_logs.py", "source_location": "L199"}, {"caller_nid": "view_logs_main", "callee": "print", "source_file": "ffa-app/tools/logging/view_logs.py", "source_location": "L202"}, {"caller_nid": "view_logs_main", "callee": "print", "source_file": "ffa-app/tools/logging/view_logs.py", "source_location": "L205"}]}